collatable/__init__.py
collatable/collator.py
collatable/extras/__init__.py
collatable/extras/dataloader.py
collatable/extras/datamodule.py
collatable/extras/dataset.py
collatable/extras/indexer.py
collatable/fields/__init__.py
collatable/fields/adjacency_field.py
collatable/fields/field.py
collatable/fields/index_field.py
collatable/fields/label_field.py
collatable/fields/list_field.py
collatable/fields/mapping_field.py
collatable/fields/metadata_field.py
collatable/fields/scalar_field.py
collatable/fields/sequence_field.py
collatable/fields/sequence_label_field.py
collatable/fields/span_field.py
collatable/fields/tensor_field.py
collatable/fields/text_field.py
collatable/py.typed
collatable/types.py
collatable/utils.py
collatable-0.5.0.dist-info/LICENSE
collatable-0.5.0.dist-info/METADATA
collatable-0.5.0.dist-info/WHEEL
collatable-0.5.0.dist-info/RECORD
