Metadata-Version: 2.3
Name: collatable
Version: 0.5.0
Summary: Constructing batched tensors for any machine learning tasks
License: MIT
Keywords: python,machine learning
Author: altescy
Author-email: altescy@fastmail.com
Requires-Python: >=3.8,<4.0
Classifier: License :: OSI Approved :: MIT License
Classifier: Programming Language :: Python :: 3
Classifier: Programming Language :: Python :: 3.8
Classifier: Programming Language :: Python :: 3.9
Classifier: Programming Language :: Python :: 3.10
Classifier: Programming Language :: Python :: 3.11
Classifier: Programming Language :: Python :: 3.12
Classifier: Programming Language :: Python :: 3.13
Requires-Dist: numpy (>=1.0.0,<1.26.4) ; python_version == "3.8"
Requires-Dist: numpy (>=1.26.4) ; python_version >= "3.9" and python_version < "4.0"
Project-URL: Homepage, https://github.com/altescy/collatable
